bblocks/projects/__init__.py
bblocks/projects/cli.py
bblocks/projects/components.py
bblocks/projects/config.py
bblocks/projects/installer.py
bblocks/projects/project.py
bblocks/projects/py.typed
bblocks_projects-0.2.2.dist-info/METADATA
bblocks_projects-0.2.2.dist-info/WHEEL
bblocks_projects-0.2.2.dist-info/entry_points.txt
bblocks_projects-0.2.2.dist-info/top_level.txt
bblocks_projects-0.2.2.dist-info/RECORD
