Metadata-Version: 2.4
Name: bblocks-projects
Version: 0.2.2
Summary: ONE Data Python project utilities - templates, tools, and workflows
Author-email: ONE Data <data@one.org>
License-Expression: MIT
Project-URL: Homepage, https://github.com/ONEcampaign/bblocks-projects
Project-URL: Repository, https://github.com/ONEcampaign/bblocks-projects
Project-URL: Issues, https://github.com/ONEcampaign/bblocks-projects/issues
Keywords: bblocks,template,copier,python,cli,project-generator,utilities
Classifier: Development Status :: 4 - Beta
Classifier: Intended Audience :: Developers
Classifier: Programming Language :: Python :: 3
Classifier: Programming Language :: Python :: 3.11
Classifier: Programming Language :: Python :: 3.12
Classifier: Programming Language :: Python :: 3.13
Classifier: Topic :: Software Development :: Code Generators
Classifier: Topic :: Software Development :: Libraries :: Python Modules
Requires-Python: >=3.11
Requires-Dist: copier>=9.0.0
Requires-Dist: typer>=0.12.0
Requires-Dist: rich>=13.0.0
Requires-Dist: toml>=0.10.2
